Flask_Log_Request_ID-0.10.0.dist-info/DESCRIPTION.rst
Flask_Log_Request_ID-0.10.0.dist-info/METADATA
Flask_Log_Request_ID-0.10.0.dist-info/RECORD
Flask_Log_Request_ID-0.10.0.dist-info/WHEEL
Flask_Log_Request_ID-0.10.0.dist-info/metadata.json
Flask_Log_Request_ID-0.10.0.dist-info/top_level.txt
flask_log_request_id/__init__.py
flask_log_request_id/ctx_fetcher.py
flask_log_request_id/filters.py
flask_log_request_id/parser.py
flask_log_request_id/request_id.py
flask_log_request_id/extras/__init__.py
flask_log_request_id/extras/celery.py
