Metadata-Version: 2.0
Name: Flask-Log-Request-ID
Version: 0.10.0
Summary: Flask extension that can parse and handle multiple types of request-id sent by request processors like Amazon ELB, Heroku or any multi-tier infrastructure as the one used for microservices.
Home-page: http://github.com/Workable/flask-log-request-id
Author: Konstantinos Paliouras
Author-email: squarious@gmail.com
License: MIT
Platform: any
Classifier: Environment :: Web Environment
Classifier: Intended Audience :: Developers
Classifier: License :: OSI Approved :: MIT License
Classifier: Operating System :: OS Independent
Classifier: Programming Language :: Python
Classifier: Programming Language :: Python :: 3
Classifier: Topic :: Software Development :: Libraries :: Python Modules
Requires-Dist: Flask (>=0.8)
Provides-Extra: celery
Requires-Dist: celery (~=4.1.0); extra == 'celery'
Provides-Extra: test
Requires-Dist: nose; extra == 'test'
Requires-Dist: mock (==2.0.0); extra == 'test'
Requires-Dist: coverage (~=4.3.4); extra == 'test'
Requires-Dist: celery (~=4.1.0); extra == 'test'
